fxq/pdbc.py
fxq_pdbc-1.0.1.dist-info/METADATA
fxq_pdbc-1.0.1.dist-info/WHEEL
fxq_pdbc-1.0.1.dist-info/top_level.txt
fxq_pdbc-1.0.1.dist-info/RECORD
